mot/__init__.py
mot/core.py
mot/methods/__init__.py
mot/methods/inspyred_methods.py
mot/methods/method.py
mot/methods/particle_swarm.py
mot/methods/random_sampling.py
mot/methods/sensitivity.py
mot/methods/simulated_annealing.py
metaheuristic_optimization_tool-0.11.1.dist-info/METADATA
metaheuristic_optimization_tool-0.11.1.dist-info/WHEEL
metaheuristic_optimization_tool-0.11.1.dist-info/top_level.txt
metaheuristic_optimization_tool-0.11.1.dist-info/RECORD
