Metadata-Version: 2.1
Name: metaheuristic-optimization-tool
Version: 0.11.1
Summary: Optimization and Sampling Driver
Home-page: https://code.ornl.gov/ybb/MOT
